lykkellemainoceania/__init__.py
lykkellemainoceania/healthcheckasia1.py
lykkellemainoceania/maincalculationprogeodasia1.py
lykkellemainoceania/mainmasterprogeodasia1.py
lykkellemainoceania-0.1.2.dist-info/LICENSE
lykkellemainoceania-0.1.2.dist-info/METADATA
lykkellemainoceania-0.1.2.dist-info/WHEEL
lykkellemainoceania-0.1.2.dist-info/top_level.txt
lykkellemainoceania-0.1.2.dist-info/RECORD
